soaparse/__init__.py
soaparse/soaparse.py
soaparse-1.3.0.dist-info/METADATA
soaparse-1.3.0.dist-info/WHEEL
soaparse-1.3.0.dist-info/top_level.txt
soaparse-1.3.0.dist-info/zip-safe
soaparse-1.3.0.dist-info/RECORD
