Metadata-Version: 2.1
Name: soaparse
Version: 1.3.0
Summary: Sane, modular DNS authority (SOA) record parsing
Home-page: https://github.com/wesinator/soaparse
Author: wesinator
License: UNKNOWN
Keywords: dns
Platform: UNKNOWN
Classifier: Intended Audience :: Developers
Classifier: License :: OSI Approved :: Mozilla Public License 2.0 (MPL 2.0)
Classifier: Natural Language :: English
Classifier: Programming Language :: Python :: 3
